turtlex/__init__.py
turtlex/turtlex.py
turtlex-1.0.4.dist-info/LICENCE
turtlex-1.0.4.dist-info/METADATA
turtlex-1.0.4.dist-info/WHEEL
turtlex-1.0.4.dist-info/top_level.txt
turtlex-1.0.4.dist-info/RECORD
