Metadata-Version: 2.1
Name: turtlex
Version: 1.0.4
Summary: Python convenience functions to control turtle window appearance and behaviour
Home-page: https://github.com/edbotstudio/turtlex
Author: Clive Haworth
Author-email: clive@ed.bot
License: MIT
Project-URL: Bug Tracker, https://github.com/edbotstudio/turtlex/issues
Platform: UNKNOWN
Classifier: Programming Language :: Python :: 3
Classifier: License :: OSI Approved :: MIT License
Classifier: Operating System :: OS Independent
Requires-Python: >=3
